{
  "rulesDirectory": ["codelyzer"],
  "rules": {
    "component-class-suffix": [true, "Component"],
    "component-max-inline-declarations": true,
    "component-selector": [true, "element", "app", "kebab-case"],
    "contextual-decorator": true,
    "contextual-lifecycle": true,
    "directive-class-suffix": [true, "Directive"],
    "directive-selector": [true, "attribute", "app", "camelCase"],
    "import-destructuring-spacing": true,
    "no-attribute-decorator": true,
    "no-conflicting-lifecycle": true,
    "no-forward-ref": true,
    "no-host-metadata-property": true,
    "no-input-prefix": [true, "can", "is", "should"],
    "no-input-rename": true,
    "no-inputs-metadata-property": true,
    "no-lifecycle-call": false,
    "no-output-native": true,
    "no-output-on-prefix": true,
    "no-output-rename": true,
    "no-outputs-metadata-property": true,
    "no-pipe-impure": true,
    "no-queries-metadata-property": true,
    "no-unused-css": true,
    "prefer-inline-decorator": false,
    "prefer-output-readonly": false,
    "relative-url-prefix": true,
    "template-accessibility-alt-text": true,
    "template-accessibility-elements-content": false,
    "template-accessibility-label-for": true,
    "template-accessibility-tabindex-no-positive": false,
    "template-accessibility-table-scope": true,
    "template-accessibility-valid-aria": true,
    "template-banana-in-box": true,
    "template-click-events-have-key-events": false,
    "template-conditional-complexity": [true, 4],
    "template-cyclomatic-complexity": [true, 5],
    "template-i18n": false,
    "template-mouse-events-have-key-events": true,
    "template-no-any": true,
    "template-no-autofocus": true,
    "template-no-call-expression": false,
    "template-no-distracting-elements": true,
    "template-no-negated-async": true,
    "template-use-track-by-function": false,
    "use-component-selector": true,
    "use-component-view-encapsulation": true,
    "use-injectable-provided-in": true,
    "use-lifecycle-interface": true,
    "use-pipe-decorator": true,
    "use-pipe-transform-interface": true
  }
}
